[{"Photographer Name": "Say Cheese Production", "Photographer Location": "Rohini, Delhi", "Price": "36,000", "Services": {"Candid Photography": "₹16,000", "Cinematography": "₹20,000", "Traditional Photography": "₹18,000", "Traditional Video": "₹18,000", "Pre Wedding Photoshoot": "₹35,000", "Albums": "₹15,000"}, "Offerings": ["Candid Photography", "Traditional Photography", "Cinematic Videography", "Traditional Video", "Drones", "Albums", "Pre-Wedding Shoot", "Photobooth", "Cranes"], "Policies": ["40% Payment On Booking", "50% Payment On Date", "10% Payment After Event", "Cancellation Policy - Depends On Project And Client Situations"], "Other Information": {"Cinematographer Availability": "No", "Willing To Travel To Other Indian Cities": "Yes"}}, {"Photographer Name": "Soulmate Films", "Photographer Location": "Rohini, Delhi", "Price": "85,000", "Services": {"Candid Photography": "₹35,000", "Cinematography": "₹50,000", "Traditional Photography": "₹20,000", "Traditional Video": "₹20,000", "Pre Wedding Photoshoot": "₹50,000", "Albums": "₹15,000"}, "Offerings": ["Pre-Wedding Shoot", "Candid Photography", "Traditional Photography", "Cinematic Videography", "Traditional Video", "Drones", "Cranes", "Albums", "Photobooth"], "Policies": ["50% Payment On Booking", "40% Payment On Date", "10% Payment After Event"], "Other Information": {"Cinematographer Availability": "No", "Willing To Travel To Other Indian Cities": "Yes"}}, {"Photographer Name": "Adways Motion Pictures", "Photographer Location": "Rohini, Delhi", "Price": "1,00,000", "Services": {"Candid Photography": "₹50,000", "Cinematography": "₹50,000", "Traditional Photography": "₹30,000", "Traditional Video": "₹30,000", "Albums": "₹25,000", "Pre Wedding Photoshoot": "₹75,000"}, "Offerings": ["Candid Photography", "Traditional Photography", "Cinematic Videography", "Traditional Video", "Drones", "Cranes", "Albums"], "Policies": ["50% Payment On Booking", "25% Payment On Date", "25% Payment After Event", "Cancellation Policy - 90 Days Before Cancellation Is Free And Days Can Be Adjusted"], "Other Information": {"Cinematographer Availability": "No", "Willing To Travel To Other Indian Cities": "Yes"}}, {"Photographer Name": "Filmy Weddings", "Photographer Location": "Rohini, Delhi", "Price": "1 Reviews", "Services": {"Candid Photography": "₹35,000", "Cinematography": "₹50,000", "Traditional Photography": "₹20,000", "Traditional Video": "₹20,000", "Pre Wedding Photoshoot": "₹55,000", "Albums": "₹15,000"}, "Offerings": ["Candid Photography", "Traditional Photography", "Cinematic Videography", "Traditional Video", "Drones", "Cranes", "Albums", "Photobooth", "Pre-Wedding Shoot"], "Policies": ["40% Payment On Booking", "50% Payment On Date", "10% Payment After Event", "Cancellation Policy - Non Refundable"], "Other Information": {"Cinematographer Availability": "No", "Willing To Travel To Other Indian Cities": "Yes"}}, {"Photographer Name": "Abhinav Suyal Photography", "Photographer Location": "Rohini, Delhi", "Price": "No Reviews", "Services": {"Candid Photography": "₹15,000", "Cinematography": "₹15,000", "Traditional Video": "₹10,000", "Pre Wedding Photoshoot": "₹15,000", "Albums": "₹10,000", "Traditional Photography": "₹10,000"}, "Offerings": ["Candid Photography", "Traditional Photography", "Cinematic Videography", "Traditional Video", "Drones", "Cranes", "Albums", "Photobooth"], "Policies": ["25% Payment On Booking", "50% Payment On Date", "25% Payment After Event", "Cancellation Policy - Depends Upon The Situation"], "Other Information": {"Cinematographer Availability": "No", "Willing To Travel To Other Indian Cities": "Yes"}}, {"Photographer Name": "Fotoart India", "Photographer Location": "Rohini, Delhi", "Price": "3 Reviews", "Services": {"Candid Photography": "₹11,499", "Cinematography": "₹18,000", "Traditional Photography": "₹12,000", "Traditional Video": "₹12,000", "Pre Wedding Photoshoot": "₹11,000", "Albums": "₹20,000"}, "Offerings": ["Candid Photography", "Traditional Photography", "Cinematic Videography", "Traditional Video", "Drones", "Albums", "Pre-Wedding Shoot"], "Policies": ["20% Payment On Booking", "70% Payment On Date", "10% Payment After Event", "Cancellation Policy - Some Amount Is Refundable From Advance If Client Inform With In 1 Month."], "Other Information": {"Cinematographer Availability": "No", "Willing To Travel To Other Indian Cities": "No"}}, {"Photographer Name": "The Urban Chitrakar", "Photographer Location": "Rohini, Delhi", "Price": "60,000", "Services": {"Candid Photography": "₹25,000", "Cinematography": "₹35,000", "Traditional Photography": "₹15,000", "Traditional Video": "₹20,000", "Pre Wedding Photoshoot": "₹35,000", "Albums": "₹12,000"}, "Offerings": ["Pre-Wedding Shoot", "Candid Photography", "Traditional Photography", "Cinematic Videography", "Traditional Video", "Drones", "Cranes", "Albums"], "Policies": ["40% Payment On Booking", "50% Payment On Date", "10% Payment After Event", "Cancellation Policy - The Payment Made Is Not Refundable."], "Other Information": {"Cinematographer Availability": "No", "Willing To Travel To Other Indian Cities": "Yes"}}, {"Photographer Name": "Delhi Digital Photo Studio", "Photographer Location": "Rohini, Delhi", "Price": "33,000", "Services": {"Cinematography": "₹18,000", "Traditional Photography": "₹10,000", "Traditional Video": "₹12,000", "Pre Wedding Photoshoot": "₹25,000", "Albums": "₹20,000", "Candid Photography": "₹15,000"}, "Offerings": ["Pre-Wedding Shoot", "Candid Photography", "Traditional Photography", "Cinematic Videography", "Traditional Video", "Drones", "Cranes", "Albums", "Photobooth"], "Policies": ["25% Payment On Booking", "50% Payment On Date", "25% Payment After Event"], "Other Information": {"Cinematographer Availability": "No", "Willing To Travel To Other Indian Cities": "Yes"}}, {"Photographer Name": "Arts Of Lenses", "Photographer Location": "Rohini, Delhi", "Price": "29,000", "Services": {"Cinematography": "₹14,000", "Traditional Photography": "₹10,000", "Traditional Video": "₹9,000", "Pre Wedding Photoshoot": "₹40,000", "Albums": "₹20,000", "Candid Photography": "₹15,000"}, "Offerings": ["Pre-Wedding Shoot", "Candid Photography", "Traditional Photography", "Cinematic Videography", "Traditional Video", "Drones", "Cranes", "Albums", "Photobooth"], "Policies": ["25% Payment On Booking", "75% Payment On Date", "Cancellation Policy - If Deal Got Canceled Only 10% Will Be Refundable From The Booking Payment"], "Other Information": {"Cinematographer Availability": "No", "Willing To Travel To Other Indian Cities": "Yes"}}, {"Photographer Name": "The Knotbook", "Photographer Location": "Rohini, Delhi", "Price": "30,000", "Services": {"Candid Photography": "₹15,000", "Cinematography": "₹15,000", "Traditional Photography": "₹8,000", "Traditional Video": "₹8,000", "Pre Wedding Photoshoot": "₹15,000"}, "Offerings": ["Pre-Wedding Shoot", "Candid Photography", "Traditional Photography", "Cinematic Videography", "Traditional Video"], "Policies": ["30% Payment On Booking", "50% Payment On Date", "20% Payment After Event"], "Other Information": {"Cinematographer Availability": "No", "Willing To Travel To Other Indian Cities": "Yes"}}, {"Photographer Name": "Sains Productions", "Photographer Location": "Rohini, Delhi", "Price": "27,000", "Services": {"Candid Photography": "₹12,000", "Cinematography": "₹15,000", "Traditional Photography": "₹8,000", "Traditional Video": "₹8,000", "Pre Wedding Photoshoot": "₹40,000", "Albums": "₹8,000"}, "Offerings": ["Pre-Wedding Shoot", "Candid Photography", "Traditional Photography", "Cinematic Videography", "Traditional Video", "Albums"], "Policies": ["50% Payment On Booking", "25% Payment On Date", "25% Payment After Event"], "Other Information": {"Cinematographer Availability": "No", "Willing To Travel To Other Indian Cities": "Yes"}}, {"Photographer Name": "Dewan Studio", "Photographer Location": "Rohini, Delhi", "Price": "30,000", "Services": {"Candid Photography": "₹15,000", "Traditional Video": "₹10,000", "Pre Wedding Photoshoot": "₹15,000", "Traditional Photography": "₹10,000", "Cinematography": "₹15,000"}, "Offerings": ["Pre-Wedding Shoot", "Candid Photography", "Traditional Photography", "Cinematic Videography", "Traditional Video"], "Policies": ["20% Payment On Booking", "60% Payment On Date", "20% Payment After Event"], "Other Information": {"Cinematographer Availability": "No", "Willing To Travel To Other Indian Cities": "Yes"}}]