[{"Photographer Name": "Kalakshaya Photography", "Photographer Location": "Rajajinagar, Bangalore", "Price": "No Reviews", "Services": {"Cinematography": "₹35,000", "Traditional Photography": "₹12,000", "Traditional Video": "₹15,000", "Pre Wedding Photoshoot": "₹30,000", "Albums": "₹24,000", "Candid Photography": "₹15,000"}, "Offerings": ["Pre-Wedding Shoot", "Candid Photography", "Traditional Photography", "Cinematic Videography", "Traditional Video", "Drones", "Albums"], "Policies": ["60% Payment On Date", "10% Payment After Event", "Cancellation Policy - No Cancellation, No Refund", "30% Payment On Booking"], "Other Information": {"Cinematographer Availability": "No", "Willing To Travel To Other Indian Cities": "No"}}, {"Photographer Name": "Acchu Photography", "Photographer Location": "Bangalore, Bangalore", "Price": "20,000", "Services": {"Candid Photography": "₹20,000", "Traditional Photography": "₹15,000"}, "Offerings": ["Candid Photography", "Traditional Photography"], "Policies": ["50% Payment On Booking", "30% Payment On Date", "20% Payment After Event"], "Other Information": {"Cinematographer Availability": "No", "Willing To Travel To Other Indian Cities": "No"}}, {"Photographer Name": "Sugar And Spice Pictures", "Photographer Location": "Rajajinagar, Bangalore", "Price": "39,000", "Services": {"Candid Photography": "₹14,000", "Cinematography": "₹25,000", "Traditional Photography": "₹10,000", "Traditional Video": "₹8,000", "Pre Wedding Photoshoot": "₹15,000", "Albums": "₹15,000"}, "Offerings": ["Pre-Wedding Shoot", "Candid Photography", "Traditional Photography", "Cinematic Videography", "Traditional Video", "Drones", "Cranes", "Albums", "Photobooth"], "Policies": ["30% Payment On Booking", "40% Payment On Date", "30% Payment After Event", "Cancellation Policy - No Conditions"], "Other Information": {"Cinematographer Availability": "No", "Willing To Travel To Other Indian Cities": "Yes"}}, {"Photographer Name": "Innovative Photo Designers", "Photographer Location": "Rajajinagar, Bangalore", "Price": "60,000", "Services": {"Candid Photography": "₹20,000", "Cinematography": "₹40,000", "Traditional Photography": "₹30,000", "Traditional Video": "₹50,000", "Pre Wedding Photoshoot": "₹20,000", "Albums": "₹10,000"}, "Offerings": ["Candid Photography", "Traditional Photography", "Cinematic Videography", "Traditional Video", "Albums"], "Policies": ["50% Payment On Booking", "50% Payment After Event"], "Other Information": {"Cinematographer Availability": "No", "Willing To Travel To Other Indian Cities": "Yes"}}, {"Photographer Name": "ASV Photography", "Photographer Location": "Rajajinagar, Bangalore", "Price": "24,000", "Services": {"Cinematography": "₹8,000", "Traditional Photography": "₹7,000", "Traditional Video": "₹6,000", "Pre Wedding Photoshoot": "₹10,000", "Albums": "₹10,000", "Candid Photography": "₹16,000"}, "Offerings": ["Pre-Wedding Shoot", "Candid Photography", "Traditional Photography", "Cinematic Videography", "Traditional Video", "Drones", "Cranes", "Albums", "Photobooth"], "Policies": ["50% Payment On Booking", "30% Payment On Date", "20% Payment After Event", "Cancellation Policy - Refundable"], "Other Information": {"Cinematographer Availability": "No", "Willing To Travel To Other Indian Cities": "Yes"}}, {"Photographer Name": "Vinu Ideas Productions", "Photographer Location": "Rajajinagar, Bangalore", "Price": "40,000", "Services": {"Candid Photography": "₹15,000", "Cinematography": "₹25,000", "Pre Wedding Photoshoot": "₹20,000"}, "Offerings": ["Pre-Wedding Shoot", "Cinematic Videography", "Candid Photography", "Drones", "Cranes"], "Policies": ["25% Payment On Booking", "50% Payment On Date", "25% Payment After Event", "Cancellation Policy - You Can Change Your Dates"], "Other Information": {"Cinematographer Availability": "No", "Willing To Travel To Other Indian Cities": "Yes"}}]