[{"Photographer Name": "The Half Way Dreams Photography", "Photographer Location": "Doddanekkundi, Bangalore", "Price": "40,000", "Services": {"Traditional Photography": "₹15,000", "Traditional Video": "₹15,000", "Pre Wedding Photoshoot": "₹25,000", "Albums": "₹8,000", "Candid Photography": "₹20,000", "Cinematography": "₹20,000"}, "Offerings": ["Pre-Wedding Shoot", "Candid Photography", "Traditional Photography", "Cinematic Videography", "Traditional Video", "Albums", "Drones"], "Policies": ["50% Payment On Booking", "40% Payment On Date", "10% Payment After Event", "Cancellation Policy - As Per Agreement During Booking"], "Other Information": {"Cinematographer Availability": "No", "Willing To Travel To Other Indian Cities": "Yes"}}]