[{"Venue Name": "Karthick Palace", "Venue Location": "Kundrathur, Chennai", "Price per Plate": "4,00,000", "Event Areas": [{"event_area_name": "Karthick Palace Banquet Hall", "seating": "Indoor", "no_of_seats": "1300 Seats", "floating_capacity": "2250 Floating"}], "Services": {"\u20b94,00,000": "\u20b94,00,000"}, "Amenities": ["17 Rooms available", "17 AC Rooms", "1500 Square Feet Capacity", "50 Parking", "Bridal Room", "Parking"], "Other info": [{"Property Type": "Kalyana Mandapam, Wedding Venue"}, {"Price Type": "Time Based Rent"}, {"Decoration": "Outside Decorators Not Allowed"}, {"Food": "Outside Food Allowed"}, {"Is Room Available": "Yes"}, {"Valet Parking": "No"}, {"Allowed Cuisine": "Both"}]}, {"Venue Name": "PRR Sri Sai Mahal", "Venue Location": "Kundrathur, Chennai", "Price per Plate": "1,20,000", "Event Areas": [{"event_area_name": "PRR Sri Sai Mahal Banquet Hall", "seating": "Indoor", "no_of_seats": "600 Seats", "floating_capacity": "1050 Floating"}], "Services": {"\u20b91,20,000": "\u20b91,20,000"}, "Amenities": ["14 Rooms available", "8 AC Rooms", "8500 Square Feet Capacity", "30 Parking", "Bridal Room", "Parking"], "Other info": [{"Property Type": "Kalyana Mandapam"}, {"Price Type": "Time Based Rent"}, {"Decoration": "Outside Decorators Not Allowed"}, {"Food": "Outside Food Allowed"}, {"Is Room Available": "Yes"}, {"Valet Parking": "No"}, {"Allowed Cuisine": "Both"}]}, {"Venue Name": "Manikandan Mahal", "Venue Location": "Kundrathur, Chennai", "Price per Plate": "15,000", "Event Areas": [{"event_area_name": "Manikandan Mahal Banquet Hall", "seating": "Indoor", "no_of_seats": "200 Seats", "floating_capacity": "300 Floating"}], "Services": {"\u20b915,000": "\u20b915,000"}, "Amenities": ["2 Rooms available", "3000 Square Feet Capacity", "10 Parking", "Bridal Room", "Parking"], "Other info": [{"Property Type": "Kalyana Mandapam, Mini Hall"}, {"Price Type": "Time Based Rent"}, {"Decoration": "Outside Decorators Allowed"}, {"Food": "Outside Food Allowed"}, {"Is Room Available": "Yes"}, {"Valet Parking": "No"}, {"Allowed Cuisine": "Both"}]}, {"Venue Name": "Kiruthika Mini Hall", "Venue Location": "Kundrathur, Chennai", "Price per Plate": "20,000", "Event Areas": [{"event_area_name": "Kiruthika Mini Hall Banquet Hall", "seating": "Indoor", "no_of_seats": "200 Seats", "floating_capacity": "300 Floating"}], "Services": {"\u20b920,000": "\u20b920,000"}, "Amenities": ["1 Rooms available", "1300 Square Feet Capacity", "20 Parking"], "Other info": [{"Property Type": "Kalyana Mandapam, Mini Hall"}, {"Price Type": "Time Based Rent"}, {"Decoration": "Outside Decorators Not Allowed"}, {"Food": "Outside Food Allowed"}, {"Is Room Available": "Yes"}, {"Valet Parking": "No"}, {"Allowed Cuisine": "Veg"}]}]