[{"Venue Name": "Sudesh Banquets", "Venue Location": "Sarat Bose Road, Kolkata", "Price per Plate": "900 - 1200", "Event Areas": [{"event_area_name": "Sudesh Banquet Hall Banquet Hall", "seating": "Indoor", "no_of_seats": "200 Seats", "floating_capacity": "250 Floating"}, {"event_area_name": "Sudesh Banquet Hall 1 Banquet Hall", "seating": "Indoor", "no_of_seats": "300 Seats", "floating_capacity": "350 Floating"}], "Services": {"\u20b9900": "\u20b9900"}, "Amenities": ["29 Rooms available", "29 AC Rooms"], "Other info": [{"Property Type": "Banquet Hall"}, {"Price Type": "Cost Per Plate"}, {"Decoration": "Outside Decorators Not Allowed"}, {"Valet Parking": "No"}, {"Allowed Cuisine": "Both"}]}, {"Venue Name": "Raaj Mangalam Hall", "Venue Location": "Sarat Bose Road, Kolkata", "Price per Plate": "450 - 550", "Event Areas": [{"event_area_name": "Raaj Mangalam Hall Banquet Hall", "seating": "Indoor", "no_of_seats": "100 Seats", "floating_capacity": "200 Floating"}], "Services": {"\u20b9550": "\u20b9550"}, "Amenities": ["2 Rooms available", "2 AC Rooms", "5 Parking"], "Other info": [{"Property Type": "Banquet Hall"}, {"Price Type": "Cost Per Plate"}, {"Decoration": "Outside Decorators Not Allowed"}, {"Valet Parking": "No"}, {"Allowed Cuisine": "Both"}]}]