[{"Artist Name": "Priya Makeover Artistry", "Artist Location": "Chennai", "Price": "8,000", "Services": {"Airbrush Makeup": "₹20,000", "Bridal Makeup": "₹8,000", "Guest/Family Makeup": "₹3,000"}, "Offerings": ["Regular Makeup", "AirBrush Makeup", "Hairstyling", "Draping", "Mehendi", "Jewellery"], "Policies": ["50% Payment On Booking", "50% Payment On Date", "Cancellation Policy - Yes"], "Other Information": {"Brand Used": "Huda And International Brands", "Is Willing To Travel To Venue": "Yes", "Is Willing To Travel Other Indian Cities": "Yes", "Trial Makeup": "Adjusted In Final Payment", "Is Studio Available": "Yes"}}, {"Artist Name": "Luxe Atelier Makeover", "Artist Location": "Ramapuram, Chennai", "Price": "10,000", "Services": {"Bridal Makeup": "₹10,000", "Guest/Family Makeup": "₹5,000"}, "Offerings": ["Regular Makeup", "Hairstyling", "Draping", "Mehendi", "Jewellery"], "Policies": ["50% Payment On Booking", "50% Payment On Date", "Payment After Event - 0", "Cancellation Policy - Depends On Situation"], "Other Information": {"Brand Used": "Mac , Pac , Krylon", "Is Willing To Travel To Venue": "Yes", "Is Willing To Travel Other Indian Cities": "Yes", "Trial Makeup": "Yes (Separately Paid)", "Is Studio Available": "No"}}, {"Artist Name": "Rj Makeover Artist", "Artist Location": "Ramapuram, Chennai", "Price": "10,000", "Services": {"Bridal Makeup": "₹10,000", "Guest/Family Makeup": "₹4,000"}, "Offerings": ["Regular Makeup", "Hairstyling", "Draping"], "Policies": ["50% Payment On Booking", "50% Payment On Date", "Cancellation Policy - Depends On Situation"], "Other Information": {"Brand Used": "All International Brands", "Is Willing To Travel To Venue": "Yes", "Is Willing To Travel Other Indian Cities": "Yes", "Trial Makeup": "No Provided", "Is Studio Available": "No"}}]