[{"Artist Name": "Sree Bridal Makeup And Mehendi", "Artist Location": "Vizianagaram", "Price": "7,500", "Services": {"Guest/Family Makeup": "₹4,500", "Bridal Makeup": "₹7,500", "Airbrush Makeup": "₹14,500"}, "Offerings": ["Regular Makeup", "AirBrush Makeup", "Hairstyling", "Draping", "Mehendi"], "Policies": ["40% Payment On Booking", "60% Payment On Date", "Payment After Event - 0", "Cancellation Policy - Depends Upon Situtation"], "Other Information": {"Brand Used": "Mac, Krylon, Fashionever,Pac, Crown, Temtu, Urbindicy, Maybelline, Forever And Etc", "Is Willing To Travel To Venue": "Yes", "Is Willing To Travel Other Indian Cities": "No", "Trial Makeup": "Yes (Separately Paid)", "Is Studio Available": "No"}}]