[{"Venue Name": "BBMP Wedding Hall", "Venue Location": "Kacharakanahalli, Bangalore", "Price per Plate": "45,000", "Event Areas": [{"event_area_name": "BBMP Wedding Hall Banquet Hall", "seating": "Indoor", "no_of_seats": "200 Seats", "floating_capacity": "250 Floating"}], "Services": {"\u20b945,000": "\u20b945,000"}, "Amenities": ["2 Rooms available", "2 AC Rooms", "2000 Square Feet Capacity", "15 Parking", "Bridal Room", "Parking"], "Other info": [{"Property Type": "Banquet Hall"}, {"Price Type": "Time Based Rent"}, {"Decoration": "Outside Decorators Allowed"}, {"Food": "Outside Food Allowed"}, {"Allowed Cuisine": "Both"}]}, {"Venue Name": "RRR Party Hall", "Venue Location": "Kacharakanahalli, Bangalore", "Price per Plate": "25,000", "Event Areas": [{"event_area_name": "RRR Party Hall Banquet Hall", "seating": "Indoor", "no_of_seats": "200 Seats", "floating_capacity": "300 Floating"}], "Services": {"\u20b925,000": "\u20b925,000"}, "Amenities": ["2 Rooms available", "4000 Square Feet Capacity", "50 Parking", "Electricity Back-up", "Bridal Room", "Parking"], "Other info": [{"Property Type": "Banquet Hall"}, {"Price Type": "Time Based Rent"}, {"Decoration": "Outside Decorators Allowed"}, {"Dj": "Outside DJ Allowed"}, {"Food": "Outside Food Allowed"}, {"Valet Parking": "No"}, {"Allowed Cuisine": "Both"}]}]