[{"Venue Name": "Haris Hall", "Venue Location": "Thirumangalam, Madurai", "Price per Plate": "250", "Event Areas": [{"event_area_name": "Haris Hall Banquet Hall", "seating": "Indoor", "no_of_seats": "225 Seats", "floating_capacity": "250 Floating"}], "Services": {"\u20b9250": "\u20b9250"}, "Amenities": ["44 Rooms available", "44 AC Rooms", "5000 Square Feet Capacity", "100 Parking", "Bridal Room", "Parking"], "Other info": [{"Property Type": "Banquet Hall"}, {"Price Type": "Cost Per Plate"}, {"Decoration": "Outside Decorators Not Allowed"}, {"Valet Parking": "No"}, {"Allowed Cuisine": "Veg"}]}, {"Venue Name": "Mangalam Mahal", "Venue Location": "Thirumangalam, Madurai", "Price per Plate": "20,000", "Event Areas": [{"event_area_name": "Mangalam Mahal Banquet Hall", "seating": "Indoor", "no_of_seats": "350 Seats", "floating_capacity": "1000 Floating"}], "Services": {"\u20b920,000": "\u20b920,000"}, "Amenities": ["4 Rooms available", "1 AC Rooms", "5000 Square Feet Capacity", "200 Parking"], "Other info": [{"Property Type": "Kalyana Mandapam, Mini Hall"}, {"Price Type": "Time Based Rent"}, {"Decoration": "Outside Decorators Not Allowed"}, {"Food": "Outside Food Allowed"}, {"Is Room Available": "Yes"}, {"Valet Parking": "No"}, {"Allowed Cuisine": "Both"}]}, {"Venue Name": "Balaguru Kamaladevi Mahal", "Venue Location": "Thirumangalam, Madurai", "Price per Plate": "75,018", "Event Areas": [{"event_area_name": "Balaguru Kamaladevi Mahal Banquet Hall", "seating": "Indoor", "no_of_seats": "500 Seats", "floating_capacity": "750 Floating"}], "Services": {"\u20b975,018": "\u20b975,018"}, "Amenities": ["4 Rooms available", "2 AC Rooms", "1 Square Feet Capacity", "20 Parking", "Bridal Room", "Parking"], "Other info": [{"Property Type": "Kalyana Mandapam"}, {"Price Type": "Time Based Rent"}, {"Decoration": "Outside Decorators Not Allowed"}, {"Food": "Outside Food Allowed"}, {"Is Room Available": "Yes"}, {"Valet Parking": "No"}, {"Allowed Cuisine": "Both"}]}]