[{"Venue Name": "Hotel Abode-Terrace", "Venue Location": "Lakdi Ka Pul, Hyderabad", "Price per Plate": "1200 - 1500", "Event Areas": [{"event_area_name": "HOTEL Abode Banquet Hall", "seating": "Indoor", "no_of_seats": "350 Seats", "floating_capacity": "600 Floating"}], "Services": {"\u20b91,500": "\u20b91,500"}, "Amenities": ["82 Rooms available", "82 AC Rooms", "8000 Square Feet Capacity", "100 Parking", "Electricity Back-up", "Bridal Room", "Parking"], "Other info": [{"Property Type": "Banquet Hall"}, {"Price Type": "Cost Per Plate"}, {"Decoration": "Outside Decorators Not Allowed"}, {"Dj": "Outside DJ Allowed"}, {"Food": "Outside Food Not Allowed"}, {"Alcohol Policy": "Outside Alcohol Not Allowed"}, {"Is Room Available": "Yes"}, {"Valet Parking": "Yes"}, {"Allowed Cuisine": "Both"}]}, {"Venue Name": "The Cent Jubilicent", "Venue Location": "Lakdi Ka Pul, Hyderabad", "Price per Plate": "700 - 800", "Event Areas": [{"event_area_name": "The Cent Jubilicent Banquet Hall", "seating": "Indoor", "no_of_seats": "200 Seats", "floating_capacity": "400 Floating"}, {"event_area_name": "The Cent Congrecent Banquet Hall", "seating": "Indoor", "no_of_seats": "100 Seats", "floating_capacity": "150 Floating"}, {"event_area_name": "The Cent Vencent Banquet Hall", "seating": "Indoor", "no_of_seats": "50 Seats", "floating_capacity": "150 Floating"}], "Services": {"\u20b9800": "\u20b9800"}, "Amenities": ["60 Rooms available", "60 AC Rooms", "40 Parking"], "Other info": [{"Property Type": "Banquet Hall, Mini Hall"}, {"Price Type": "Cost Per Plate"}, {"Decoration": "Outside Decorators Allowed"}, {"Dj": "Outside DJ Allowed"}, {"Valet Parking": "Yes"}, {"Allowed Cuisine": "Both"}]}, {"Venue Name": "Best Western Hotel Patio 2", "Venue Location": "Lakdi Ka Pul, Hyderabad", "Price per Plate": "560 - 796", "Event Areas": [{"event_area_name": "Best Western Hotel Patio 1 Banquet Hall", "seating": "Indoor", "no_of_seats": "50 Seats", "floating_capacity": "75 Floating"}, {"event_area_name": "Best Western Hotel Wisteria 1 Banquet Hall", "seating": "Indoor", "no_of_seats": "100 Seats", "floating_capacity": "125 Floating"}, {"event_area_name": "Best Western Hotel Wisteria 3 Banquet Hall", "seating": "Indoor", "no_of_seats": "250 Seats", "floating_capacity": "300 Floating"}], "Services": {"\u20b9796": "\u20b9796"}, "Amenities": ["20 Rooms available", "20 AC Rooms", "100 Parking"], "Other info": [{"Property Type": "Banquet Hall"}, {"Price Type": "Cost Per Plate"}, {"Decoration": "Outside Decorators Not Allowed"}, {"Dj": "Outside DJ Allowed"}, {"Alcohol Policy": "Outside Alcohol Not Allowed"}, {"Valet Parking": "Yes"}, {"Allowed Cuisine": "Both"}]}, {"Venue Name": "", "Venue Location": "", "Price per Plate": "", "Event Areas": "", "Services": "", "Amenities": "", "Other info": ""}, {"Venue Name": "Hotel PearlGrand Flora", "Venue Location": "Lakdi Ka Pul, Hyderabad", "Price per Plate": "460 - 578", "Event Areas": [{"event_area_name": "Hotel PearlGrand Flora Banquet Hall", "seating": "Indoor", "no_of_seats": "250 Seats", "floating_capacity": "350 Floating"}], "Services": {"\u20b9460": "\u20b9460"}, "Amenities": ["39 Rooms available", "39 AC Rooms", "30 Parking"], "Other info": [{"Property Type": "Banquet Hall"}, {"Price Type": "Cost Per Plate"}, {"Decoration": "Outside Decorators Allowed"}, {"Valet Parking": "Yes"}, {"Allowed Cuisine": "Both"}]}, {"Venue Name": "Hotel Riya Grand Banquet Hall", "Venue Location": "Lakdi Ka Pul, Hyderabad", "Price per Plate": "120 - 250", "Event Areas": [{"event_area_name": "Hotel Riya Grand Banquet Hall Banquet Hall", "seating": "Indoor", "no_of_seats": "50 Seats", "floating_capacity": "100 Floating"}], "Services": {"\u20b9120": "\u20b9120"}, "Amenities": ["53 Rooms available", "53 AC Rooms", "15 Parking"], "Other info": [{"Property Type": "Banquet Hall, Mini Hall"}, {"Price Type": "Cost Per Plate"}, {"Decoration": "Outside Decorators Allowed"}, {"Dj": "Outside DJ Allowed"}, {"Alcohol Policy": "Outside Alcohol Allowed"}, {"Valet Parking": "Yes"}, {"Allowed Cuisine": "Both"}]}, {"Venue Name": "The Central Court Hotel", "Venue Location": "Lakdi Ka Pul, Hyderabad", "Price per Plate": "550 - 650", "Event Areas": [{"event_area_name": "The Central Court Hotel Banquet Hall", "seating": "Indoor", "no_of_seats": "175 Seats", "floating_capacity": "400 Floating"}], "Services": {"\u20b9650": "\u20b9650"}, "Amenities": ["70 Rooms available", "70 AC Rooms", "8000 Square Feet Capacity", "60 Parking"], "Other info": [{"Property Type": "Banquet Hall, Mini Hall"}, {"Price Type": "Cost Per Plate"}, {"Decoration": "Outside Decorators Allowed"}, {"Dj": "Outside DJ Allowed"}, {"Alcohol Policy": "Outside Alcohol Allowed"}, {"Valet Parking": "Yes"}, {"Allowed Cuisine": "Both"}]}, {"Venue Name": "Aziz Mansion Function Palace", "Venue Location": "Lakdi Ka Pul, Hyderabad", "Price per Plate": "600 - 650", "Event Areas": [{"event_area_name": "Aziz Mansion Function Palace Banquet Hall", "seating": "Indoor", "no_of_seats": "400 Seats", "floating_capacity": "800 Floating"}], "Services": {"\u20b9600": "\u20b9600"}, "Amenities": ["1 Rooms available", "1 AC Rooms", "10 Parking"], "Other info": [{"Property Type": "Banquet Hall"}, {"Price Type": "Cost Per Plate"}, {"Decoration": "Outside Decorators Allowed"}, {"Valet Parking": "No"}, {"Allowed Cuisine": "Both"}]}, {"Venue Name": "Maruti Garden Function Hall", "Venue Location": "Lakdi Ka Pul, Hyderabad", "Price per Plate": "600", "Event Areas": [{"event_area_name": "Maruti Garden Function Hall Banquet Hall", "seating": "Indoor", "no_of_seats": "500 Seats", "floating_capacity": "750 Floating"}], "Services": {"\u20b9600": "\u20b9600"}, "Amenities": ["12 Rooms available", "12 AC Rooms", "150 Parking", "Electricity Back-up", "Bridal Room"], "Other info": [{"Property Type": "Wedding Venue, Convention Hall, Banquet Hall"}, {"Price Type": "Both"}, {"Decoration": "Outside Decorators Allowed"}, {"Dj": "Outside DJ Allowed"}, {"Food": "Outside Food Allowed"}, {"Valet Parking": "Yes"}, {"Allowed Cuisine": "Veg"}]}, {"Venue Name": "Yousuf Function Hall", "Venue Location": "Lakdi Ka Pul, Hyderabad", "Price per Plate": "50,000", "Event Areas": [{"event_area_name": "Yousuf Function Hall Banquet Hall", "seating": "Indoor", "no_of_seats": "350 Seats", "floating_capacity": "525 Floating"}], "Services": {"\u20b950,000": "\u20b950,000"}, "Amenities": ["2 Rooms available", "2 AC Rooms", "8000 Square Feet Capacity", "30 Parking", "Electricity Back-up", "Bridal Room", "Parking"], "Other info": [{"Property Type": "Wedding Venue"}, {"Price Type": "Time Based Rent"}, {"Decoration": "Outside Decorators Allowed"}, {"Food": "Outside Food Allowed"}, {"Is Room Available": "Yes"}, {"Valet Parking": "No"}, {"Allowed Cuisine": "Both"}]}, {"Venue Name": "Shah Function Plaza", "Venue Location": "Lakdi Ka Pul, Hyderabad", "Price per Plate": "1,80,000", "Event Areas": [{"event_area_name": "Shah Function Plaza Banquet Hall", "seating": "Indoor", "no_of_seats": "1000 Seats", "floating_capacity": "1500 Floating"}], "Services": {"\u20b91,80,000": "\u20b91,80,000"}, "Amenities": ["2 Rooms available", "2 AC Rooms", "10 Parking"], "Other info": [{"Property Type": "Wedding Venue, Convention Hall"}, {"Price Type": "Time Based Rent"}, {"Decoration": "Outside Decorators Allowed"}, {"Food": "Outside Food Allowed"}, {"Valet Parking": "No"}, {"Allowed Cuisine": "Both"}]}]