[{"Venue Name": "Rajesh Marriage Contractor In Tirumala And Kalyanamandapam", "Venue Location": "Tirumala, Tirupati", "Price per Plate": "55,000", "Event Areas": [{"event_area_name": "Rajesh Marriage Contractor In Tirumala And Kalyanamandapam Banquet Hall", "seating": "Indoor", "no_of_seats": "100 Seats", "floating_capacity": "250 Floating"}], "Services": {"\u20b955,000": "\u20b955,000"}, "Amenities": ["20 Rooms available", "10 AC Rooms", "1200 Square Feet Capacity", "50 Parking", "Electricity Back-up", "Bridal Room", "Parking"], "Other info": [{"Property Type": "Banquet Hall"}, {"Price Type": "Time Based Rent"}, {"Decoration": "Outside Decorators Not Allowed"}, {"Food": "Outside Food Not Allowed"}, {"Is Room Available": "Yes"}, {"Valet Parking": "Yes"}, {"Allowed Cuisine": "Veg"}]}, {"Venue Name": "Gubba Choultry Kalyana Mandapam", "Venue Location": "Tirumala, Tirupati", "Price per Plate": "50,000", "Event Areas": [{"event_area_name": "Gubba Choultry Kalyana Mandapam Banquet Hall", "seating": "Indoor", "no_of_seats": "200 Seats", "floating_capacity": "300 Floating"}], "Services": {"\u20b950,000": "\u20b950,000"}, "Amenities": ["30 Rooms available", "8 AC Rooms", "1200 Square Feet Capacity", "15 Parking"], "Other info": [{"Property Type": "Banquet Hall"}, {"Price Type": "Time Based Rent"}, {"Food": "Outside Food Allowed"}, {"Allowed Cuisine": "Veg"}]}, {"Venue Name": "Sri Prativadi Bhayankar Mutt", "Venue Location": "Tirumala, Tirupati", "Price per Plate": "1000 - 1200", "Event Areas": [{"event_area_name": "Sri Prativadi Bhayankar Mutt Banquet Hall", "seating": "Indoor", "no_of_seats": "150 Seats", "floating_capacity": "200 Floating"}], "Services": {"\u20b91,200": "\u20b91,200"}, "Amenities": ["4500 Square Feet Capacity"], "Other info": [{"Property Type": "Convention Hall"}, {"Price Type": "Cost Per Plate"}, {"Allowed Cuisine": "Both"}]}, {"Venue Name": "S Raja Marriage Contractor Kalyanamandapam", "Venue Location": "Tirumala, Tirupati", "Price per Plate": "50,000", "Event Areas": [{"event_area_name": "S Raja Marriage Contractor Kalyanamandapam Banquet Hall", "seating": "Indoor", "no_of_seats": "275 Seats", "floating_capacity": "425 Floating"}], "Services": {"\u20b950,000": "\u20b950,000"}, "Amenities": ["25 Rooms available", "15 AC Rooms", "1999 Square Feet Capacity", "35 Parking"], "Other info": [{"Property Type": "Banquet Hall"}, {"Price Type": "Time Based Rent"}, {"Food": "Outside Food Allowed"}, {"Allowed Cuisine": "Veg"}]}, {"Venue Name": "Fortune Select Grand Ridge", "Venue Location": "Tiruchanur, Tirupati", "Price per Plate": "", "Event Areas": [], "Services": {"\u20b9918": "\u20b9918"}, "Amenities": [], "Other info": []}]