[{"Venue Name": "The Club Greenery", "Venue Location": "Mysore Road, Bangalore", "Price per Plate": "354 - 643", "Event Areas": [{"event_area_name": "The Club Greenery Banquet Hall", "seating": "Indoor", "no_of_seats": "500 Seats", "floating_capacity": "1000 Floating"}, {"event_area_name": "The Club Poolside Banquet Hall", "seating": "Indoor", "no_of_seats": "200 Seats", "floating_capacity": "700 Floating"}, {"event_area_name": "The Club Shuttle Court Banquet Hall", "seating": "Indoor", "no_of_seats": "400 Seats", "floating_capacity": "750 Floating"}, {"event_area_name": "The Club Banquet Hall Banquet Hall", "seating": "Indoor", "no_of_seats": "125 Seats", "floating_capacity": "200 Floating"}], "Services": {"\u20b9643": "\u20b9643"}, "Amenities": ["47 Rooms available", "47 AC Rooms", "150 Parking"], "Other info": [{"Property Type": "Banquet Hall, Resort"}, {"Price Type": "Cost Per Plate"}, {"Decoration": "Outside Decorators Not Allowed"}, {"Dj": "Outside DJ Allowed"}, {"Alcohol Policy": "Outside Alcohol Not Allowed"}, {"Valet Parking": "Yes"}, {"Allowed Cuisine": "Both"}]}, {"Venue Name": "Ruppis Hotel And Resort Banquet Hall", "Venue Location": "Mysore Road, Bangalore", "Price per Plate": "767 - 1180", "Event Areas": [{"event_area_name": "Ruppis Hotel And Resort Banquet Hall Banquet Hall", "seating": "Indoor", "no_of_seats": "150 Seats", "floating_capacity": "200 Floating"}, {"event_area_name": "Ruppis Hotel And Resort Open Lawn Banquet Hall", "seating": "Indoor", "no_of_seats": "1200 Seats", "floating_capacity": "1800 Floating"}], "Services": {"\u20b9767": "\u20b9767"}, "Amenities": ["24 Rooms available", "12 AC Rooms", "100 Parking"], "Other info": [{"Property Type": "Banquet Hall, Convention Hall, Resort, Wedding Venue"}, {"Price Type": "Both"}, {"Decoration": "Outside Decorators Allowed"}, {"Dj": "Outside DJ Allowed"}, {"Food": "Outside Food Allowed"}, {"Alcohol Policy": "Outside Alcohol Not Allowed"}, {"Valet Parking": "No"}, {"Allowed Cuisine": "Both"}]}, {"Venue Name": "The Garden Asia Resort 1st Lawn", "Venue Location": "Mysore Road, Bangalore", "Price per Plate": "999 - 999", "Event Areas": [{"event_area_name": "The Garden Asia Resort 1st Lawn Banquet Hall", "seating": "Indoor", "no_of_seats": "1500 Seats", "floating_capacity": "2250 Floating"}, {"event_area_name": "The Garden Asia Resort 2nd Lawn Banquet Hall", "seating": "Indoor", "no_of_seats": "1000 Seats", "floating_capacity": "1500 Floating"}, {"event_area_name": "The Garden Asia Resort First Floor Banquet Hall Banquet Hall", "seating": "Indoor", "no_of_seats": "150 Seats", "floating_capacity": "300 Floating"}, {"event_area_name": "The Garden Asia Resort Lavender Hall Banquet Hall", "seating": "Indoor", "no_of_seats": "400 Seats", "floating_capacity": "1000 Floating"}, {"event_area_name": "The Garden Asia Resort 3rd Lawn Banquet Hall", "seating": "Indoor", "no_of_seats": "500 Seats", "floating_capacity": "750 Floating"}, {"event_area_name": "The Garden Asia Resort TG Hall Banquet Hall", "seating": "Indoor", "no_of_seats": "150 Seats", "floating_capacity": "300 Floating"}], "Services": {"\u20b9999": "\u20b9999"}, "Amenities": ["66 Rooms available", "66 AC Rooms", "300 Parking"], "Other info": [{"Property Type": "Convention Hall, Banquet Hall, Resort, Wedding Venue"}, {"Price Type": "Both"}, {"Decoration": "Outside Decorators Allowed"}, {"Dj": "Outside DJ Allowed"}, {"Food": "Outside Food Allowed"}, {"Valet Parking": "No"}, {"Allowed Cuisine": "Both"}]}, {"Venue Name": "Shree Royal Airavatha Convention", "Venue Location": "Mysore Road, Bangalore", "Price per Plate": "410", "Event Areas": [{"event_area_name": "Shree Royal Airavatha Convention Banquet Hall", "seating": "Indoor", "no_of_seats": "600 Seats", "floating_capacity": "900 Floating"}, {"event_area_name": "Shree Royal Airavatha Party Hall Banquet Hall", "seating": "Indoor", "no_of_seats": "175 Seats", "floating_capacity": "350 Floating"}, {"event_area_name": "Shree Royal Airavatha Mini Hall Banquet Hall", "seating": "Indoor", "no_of_seats": "75 Seats", "floating_capacity": "100 Floating"}], "Services": {"\u20b9410": "\u20b9410"}, "Amenities": ["26 Rooms available", "26 AC Rooms", "250 Parking"], "Other info": [{"Property Type": "Convention Hall, Banquet Hall, Mini Hall, Wedding Venue"}, {"Price Type": "Cost Per Plate"}, {"Decoration": "Outside Decorators Allowed"}, {"Food": "Outside Food Allowed"}, {"Valet Parking": "No"}, {"Allowed Cuisine": "Veg"}]}, {"Venue Name": "Hotel Sandesh The Prince", "Venue Location": "Mysore Road, Bangalore", "Price per Plate": "699 - 899", "Event Areas": [{"event_area_name": "Hotel Sandesh The Prince Hall 1 Banquet Hall", "seating": "Indoor", "no_of_seats": "200 Seats", "floating_capacity": "300 Floating"}, {"event_area_name": "Hotel Sandesh The Prince Hall 2 Banquet Hall", "seating": "Indoor", "no_of_seats": "400 Seats", "floating_capacity": "500 Floating"}], "Services": {"\u20b9699": "\u20b9699"}, "Amenities": ["44 Rooms available", "44 AC Rooms", "50 Parking"], "Other info": [{"Property Type": "Banquet Hall"}, {"Price Type": "Cost Per Plate"}, {"Decoration": "Outside Decorators Not Allowed"}, {"Valet Parking": "No"}, {"Allowed Cuisine": "Both"}]}, {"Venue Name": "", "Venue Location": "", "Price per Plate": "", "Event Areas": "", "Services": "", "Amenities": "", "Other info": ""}, {"Venue Name": "Sri Krishna Nandagokula Party Hall", "Venue Location": "Mysore Road, Bangalore", "Price per Plate": "350", "Event Areas": [{"event_area_name": "Sri Krishna Nandagokula Party Hall Banquet Hall", "seating": "Indoor", "no_of_seats": "100 Seats", "floating_capacity": "150 Floating"}], "Services": {"\u20b9350": "\u20b9350"}, "Amenities": ["1 Rooms available", "1 AC Rooms", "20 Parking"], "Other info": [{"Property Type": "Banquet Hall, Mini Hall, Wedding Venue"}, {"Price Type": "Cost Per Plate"}, {"Decoration": "Outside Decorators Allowed"}, {"Dj": "Outside DJ Allowed"}, {"Valet Parking": "No"}, {"Allowed Cuisine": "Veg"}]}, {"Venue Name": "Abdul Wahid Function Hall 2", "Venue Location": "Mysore Road, Bangalore", "Price per Plate": "599 - 799", "Event Areas": [{"event_area_name": "Abdul Wahid Function Hall 2 Banquet Hall", "seating": "Indoor", "no_of_seats": "1000 Seats", "floating_capacity": "1200 Floating"}], "Services": {"\u20b9599": "\u20b9599"}, "Amenities": ["4 Rooms available", "4 AC Rooms", "10 Parking"], "Other info": [{"Property Type": "Banquet Hall"}, {"Price Type": "Cost Per Plate"}, {"Decoration": "Outside Decorators Not Allowed"}, {"Valet Parking": "Yes"}, {"Allowed Cuisine": "Both"}]}, {"Venue Name": "H K Function Hall", "Venue Location": "Mysore Road, Bangalore", "Price per Plate": "800 - 1000", "Event Areas": [{"event_area_name": "H K Function Hall Banquet Hall", "seating": "Indoor", "no_of_seats": "500 Seats", "floating_capacity": "600 Floating"}], "Services": {"\u20b9800": "\u20b9800"}, "Amenities": ["2 AC Rooms", "50 Parking"], "Other info": [{"Property Type": "Banquet Hall"}, {"Price Type": "Cost Per Plate"}, {"Decoration": "Outside Decorators Not Allowed"}, {"Valet Parking": "No"}, {"Allowed Cuisine": "Both"}]}, {"Venue Name": "Rosetta By Ferns", "Venue Location": "Mysore Road, Bangalore", "Price per Plate": "800 - 950", "Event Areas": [{"event_area_name": "Rosetta By Ferns Banquet Hall", "seating": "Indoor", "no_of_seats": "600 Seats", "floating_capacity": "650 Floating"}], "Services": {"\u20b9950": "\u20b9950"}, "Amenities": ["126 AC Rooms", "200 Parking"], "Other info": [{"Property Type": "Banquet Hall"}, {"Price Type": "Cost Per Plate"}, {"Decoration": "Outside Decorators Not Allowed"}, {"Valet Parking": "No"}, {"Allowed Cuisine": "Both"}]}, {"Venue Name": "Vattika Vegetarian Restaurant", "Venue Location": "Mysore Road, Bangalore", "Price per Plate": "850 - 1050", "Event Areas": [{"event_area_name": "Vattika Vegetarian Restaurant Lawn", "seating": "Outdoor", "no_of_seats": "120 Seats", "floating_capacity": "150 Floating"}], "Services": {"\u20b91,050": "\u20b91,050"}, "Amenities": ["3 Rooms available", "3 AC Rooms", "1500 Square Feet Capacity", "10 Parking", "Bridal Room", "Parking"], "Other info": [{"Property Type": "Lawn"}, {"Price Type": "Cost Per Plate"}, {"Decoration": "Outside Decorators Allowed"}, {"Allowed Cuisine": "Both"}]}, {"Venue Name": "White Palace Convention Hall", "Venue Location": "Mysore Road, Bangalore", "Price per Plate": "6,00,000", "Event Areas": [{"event_area_name": "White Palace Convention Hall Banquet Hall", "seating": "Indoor", "no_of_seats": "800 Seats", "floating_capacity": "1200 Floating"}], "Services": {"\u20b96,00,000": "\u20b96,00,000"}, "Amenities": ["32 Rooms available", "32 AC Rooms", "200 Parking"], "Other info": [{"Property Type": "Convention Hall"}, {"Price Type": "Time Based Rent"}, {"Decoration": "Outside Decorators Allowed"}, {"Food": "Outside Food Allowed"}, {"Valet Parking": "No"}, {"Allowed Cuisine": "Veg"}]}, {"Venue Name": "Sri HD Devegowda Samudaya Bhavana", "Venue Location": "Mysore Road, Bangalore", "Price per Plate": "45,018", "Event Areas": [{"event_area_name": "Sri HD Devegowda Samudaya Bhavana Banquet Hall", "seating": "Indoor", "no_of_seats": "500 Seats", "floating_capacity": "750 Floating"}], "Services": {"\u20b945,018": "\u20b945,018"}, "Amenities": ["10 Rooms available", "100 Parking"], "Other info": [{"Property Type": "Convention Hall"}, {"Price Type": "Time Based Rent"}, {"Decoration": "Outside Decorators Not Allowed"}, {"Food": "Outside Food Not Allowed"}, {"Valet Parking": "No"}, {"Allowed Cuisine": "Veg"}]}, {"Venue Name": "Sri Mahadeshwara Marriage Hall", "Venue Location": "Mysore Road, Bangalore", "Price per Plate": "95,018", "Event Areas": [{"event_area_name": "Sri Mahadeshwara Marriage Hall Banquet Hall", "seating": "Indoor", "no_of_seats": "600 Seats", "floating_capacity": "900 Floating"}], "Services": {"\u20b995,018": "\u20b995,018"}, "Amenities": ["10 Rooms available", "50 Parking"], "Other info": [{"Property Type": "Kalyana Mandapam"}, {"Price Type": "Time Based Rent"}, {"Decoration": "Outside Decorators Not Allowed"}, {"Food": "Outside Food Allowed"}, {"Valet Parking": "No"}, {"Allowed Cuisine": "Veg"}]}, {"Venue Name": "Sri Chikkamma Bhavan", "Venue Location": "Mysore Road, Bangalore", "Price per Plate": "50,018", "Event Areas": [{"event_area_name": "Sri Chikkamma Bhavan Banquet Hall", "seating": "Indoor", "no_of_seats": "450 Seats", "floating_capacity": "675 Floating"}], "Services": {"\u20b950,018": "\u20b950,018"}, "Amenities": ["11 Rooms available", "50 Parking"], "Other info": [{"Property Type": "Kalyana Mandapam"}, {"Price Type": "Time Based Rent"}, {"Decoration": "Outside Decorators Not Allowed"}, {"Food": "Outside Food Allowed"}, {"Valet Parking": "No"}, {"Allowed Cuisine": "Veg"}]}, {"Venue Name": "MR Convention Hall", "Venue Location": "Mysore Road, Bangalore", "Price per Plate": "4,00,000", "Event Areas": [{"event_area_name": "MR Convention Hall Banquet Hall", "seating": "Indoor", "no_of_seats": "600 Seats", "floating_capacity": "900 Floating"}], "Services": {"\u20b94,00,000": "\u20b94,00,000"}, "Amenities": ["10 Rooms available", "10 AC Rooms", "100 Parking"], "Other info": [{"Property Type": "Convention Hall"}, {"Price Type": "Time Based Rent"}, {"Decoration": "Outside Decorators Not Allowed"}, {"Food": "Outside Food Allowed"}, {"Valet Parking": "No"}, {"Allowed Cuisine": "Veg"}]}, {"Venue Name": "M Siri Convention Hall", "Venue Location": "Mysore Road, Bangalore", "Price per Plate": "1,00,000", "Event Areas": [{"event_area_name": "M Siri Open Lawn Banquet Hall", "seating": "Indoor", "no_of_seats": "1800 Seats", "floating_capacity": "2700 Floating"}, {"event_area_name": "M Siri Convention Hall Banquet Hall", "seating": "Indoor", "no_of_seats": "500 Seats", "floating_capacity": "750 Floating"}], "Services": {"\u20b91,00,000": "\u20b91,00,000"}, "Amenities": ["10 Rooms available", "10 AC Rooms", "200 Parking"], "Other info": [{"Property Type": "Convention Hall"}, {"Price Type": "Time Based Rent"}, {"Decoration": "Outside Decorators Not Allowed"}, {"Food": "Outside Food Not Allowed"}, {"Valet Parking": "No"}, {"Allowed Cuisine": "Veg"}]}]