[{"Venue Name": "Shiv Garden Greens", "Venue Location": "Greater Noida, Delhi", "Price per Plate": "1500 - 1800", "Event Areas": [{"event_area_name": "Shiv Garden Greens 1 Banquet Hall", "seating": "Indoor", "no_of_seats": "200 Seats", "floating_capacity": "225 Floating"}, {"event_area_name": "Shiv Garden Greens 2 Banquet Hall", "seating": "Indoor", "no_of_seats": "400 Seats", "floating_capacity": "425 Floating"}, {"event_area_name": "Shiv Garden Greens Lawn 1 Banquet Hall", "seating": "Indoor", "no_of_seats": "500 Seats", "floating_capacity": "750 Floating"}, {"event_area_name": "Shiv Garden Greens Lawn 2 Banquet Hall", "seating": "Indoor", "no_of_seats": "1500 Seats", "floating_capacity": "2250 Floating"}], "Services": {"\u20b91,500": "\u20b91,500"}, "Amenities": ["48 AC Rooms"], "Other info": [{"Property Type": "Banquet Hall, Wedding Venue, Lawn"}, {"Price Type": "Both"}, {"Decoration": "Outside Decorators Not Allowed"}, {"Food": "Outside Food Allowed"}, {"Valet Parking": "No"}, {"Allowed Cuisine": "Both"}]}]