[{"Venue Name": "The Hotel Anmol Continental", "Venue Location": "Governor Peta, Vijayawada", "Price per Plate": "375 - 500", "Event Areas": [{"event_area_name": "The Hotel Anmol Continental Banquet Hall", "seating": "Indoor", "no_of_seats": "250 Seats", "floating_capacity": "350 Floating"}], "Services": {"\u20b9375": "\u20b9375"}, "Amenities": ["32 Rooms available", "32 AC Rooms", "10 Parking"], "Other info": [{"Property Type": "Banquet Hall, Mini Hall"}, {"Price Type": "Cost Per Plate"}, {"Decoration": "Outside Decorators Allowed"}, {"Dj": "Outside DJ Allowed"}, {"Alcohol Policy": "Outside Alcohol Allowed"}, {"Valet Parking": "Yes"}, {"Allowed Cuisine": "Veg"}]}, {"Venue Name": "Continental Park Hotel", "Venue Location": "Governor Peta, Vijayawada", "Price per Plate": "400 - 500", "Event Areas": [{"event_area_name": "Continental Park Hotel Banquet Hall", "seating": "Indoor", "no_of_seats": "125 Seats", "floating_capacity": "150 Floating"}], "Services": {"\u20b9400": "\u20b9400"}, "Amenities": ["36 Rooms available", "36 AC Rooms", "10 Parking"], "Other info": [{"Property Type": "Banquet Hall, Mini Hall"}, {"Price Type": "Cost Per Plate"}, {"Decoration": "Outside Decorators Allowed"}, {"Dj": "Outside DJ Allowed"}, {"Alcohol Policy": "Outside Alcohol Allowed"}, {"Valet Parking": "No"}, {"Allowed Cuisine": "Veg"}]}, {"Venue Name": "Hotel Krishna Residency", "Venue Location": "Governor Peta, Vijayawada", "Price per Plate": "400", "Event Areas": [{"event_area_name": "Hotel Krishna Residency Banquet Hall", "seating": "Indoor", "no_of_seats": "50 Seats", "floating_capacity": "100 Floating"}], "Services": {"\u20b9400": "\u20b9400"}, "Amenities": ["51 Rooms available", "1 AC Rooms", "20 Parking"], "Other info": [{"Property Type": "Banquet Hall, Mini Hall"}, {"Price Type": "Cost Per Plate"}, {"Decoration": "Outside Decorators Allowed"}, {"Alcohol Policy": "Outside Alcohol Allowed"}, {"Valet Parking": "No"}, {"Allowed Cuisine": "Veg"}]}, {"Venue Name": "Centre Side Banquet Hall", "Venue Location": "Governor Peta, Vijayawada", "Price per Plate": "618 - 868", "Event Areas": [{"event_area_name": "Centre Side Banquet Hall Banquet Hall", "seating": "Indoor", "no_of_seats": "250 Seats", "floating_capacity": "375 Floating"}], "Services": {"\u20b9618": "\u20b9618"}, "Amenities": ["2 Rooms available", "2 AC Rooms", "40 Parking"], "Other info": [{"Property Type": "Banquet Hall"}, {"Price Type": "Cost Per Plate"}, {"Decoration": "Outside Decorators Not Allowed"}, {"Valet Parking": "No"}, {"Allowed Cuisine": "Both"}]}, {"Venue Name": "Hotel Kosala Utsav", "Venue Location": "Governor Peta, Vijayawada", "Price per Plate": "350 - 450", "Event Areas": [{"event_area_name": "Hotel Kosala Utsav Banquet Hall", "seating": "Indoor", "no_of_seats": "75 Seats", "floating_capacity": "100 Floating"}], "Services": {"\u20b9350": "\u20b9350"}, "Amenities": ["3 Rooms available", "3 AC Rooms", "20 Parking"], "Other info": [{"Property Type": "Banquet Hall, Mini Hall"}, {"Price Type": "Cost Per Plate"}, {"Decoration": "Outside Decorators Allowed"}, {"Dj": "Outside DJ Allowed"}, {"Valet Parking": "Yes"}, {"Allowed Cuisine": "Veg"}]}, {"Venue Name": "Hotel Raj Towers", "Venue Location": "Governor Peta, Vijayawada", "Price per Plate": "468 - 568", "Event Areas": [{"event_area_name": "Raj Towers Banquet Hall 1 Banquet Hall", "seating": "Indoor", "no_of_seats": "500 Seats", "floating_capacity": "650 Floating"}, {"event_area_name": "Raj Towers Banquet Hall 2 Banquet Hall", "seating": "Indoor", "no_of_seats": "200 Seats", "floating_capacity": "350 Floating"}], "Services": {"\u20b9468": "\u20b9468"}, "Amenities": ["42 Rooms available", "42 AC Rooms", "25 Parking"], "Other info": [{"Property Type": "Banquet Hall"}, {"Price Type": "Cost Per Plate"}, {"Decoration": "Outside Decorators Not Allowed"}, {"Valet Parking": "No"}, {"Allowed Cuisine": "Both"}]}, {"Venue Name": "Hotel Swarna Palace", "Venue Location": "Governor Peta, Vijayawada", "Price per Plate": "15,000", "Event Areas": [{"event_area_name": "Hotel Swarna Palace Sangamam Banquet Hall Banquet Hall", "seating": "Indoor", "no_of_seats": "225 Seats", "floating_capacity": "350 Floating"}, {"event_area_name": "Hotel Swarna Palace Sammelan Banquet Hall Banquet Hall", "seating": "Indoor", "no_of_seats": "100 Seats", "floating_capacity": "150 Floating"}], "Services": {"\u20b915,000": "\u20b915,000"}, "Amenities": ["20 Parking"], "Other info": [{"Property Type": "Wedding Venue"}, {"Price Type": "Time Based Rent"}, {"Decoration": "Outside Decorators Not Allowed"}, {"Food": "Outside Food Not Allowed"}, {"Valet Parking": "No"}, {"Allowed Cuisine": "Veg"}]}]