[{"Artist Name": "Femina Makeup Artistry", "Artist Location": "Kaval Bairasandra, Bangalore", "Price": "15,000", "Services": {"Bridal Makeup": "₹15,000", "Guest/Family Makeup": "₹10,000"}, "Offerings": ["Regular Makeup", "Hairstyling", "Draping", "Mehendi"], "Policies": ["50% Payment On Booking", "50% Payment On Date", "Cancellation Policy - Please Note That Once You Booked Amount Is Non Refundable"], "Other Information": {"Brand Used": "MAC,Huda Beauty,PAC, Makeup Revolution", "Is Willing To Travel To Venue": "Yes", "Is Willing To Travel Other Indian Cities": "Yes", "Trial Makeup": "Yes (Separately Paid)", "Is Studio Available": "No"}}]