[{"Artist Name": "PS Makeovers", "Artist Location": "Kilari Road, Bangalore", "Price": "6,000", "Services": {"Bridal Makeup": "₹6,000", "Guest/Family Makeup": "₹2,000"}, "Offerings": ["Regular Makeup", "Hairstyling", "Draping", "Jewellery"], "Policies": ["50% Payment On Booking", "50% Payment On Date", "Cancellation Policy - Advance Not Refunded"], "Other Information": {"Brand Used": "Kryolan", "Is Willing To Travel To Venue": "Yes", "Is Willing To Travel Other Indian Cities": "Yes", "Trial Makeup": "Yes (Separately Paid)", "Is Studio Available": "No"}}]