[{"Planner Name": "El Recuerdo", "Planner Location": "Hadapsar, Pune", "Price": "5 Reviews", "Services": {"Starting Price": "₹5,00,000"}, "Offerings": ["Trousseau Preparations", "DJ/Music", "Decor", "Photography Services", "Honeymoon", "Service Staff", "Invitations", "Gifts", "Celebrity Invites"], "Policies": ["50% Payment On Booking", "50% Payment On Date", "Cancellation Policy - Booking Amount Of 15% Will Not Be Refunded Upon Cancellation"], "Other Information": {"In House Services": "Trousseau Preparations, DJ/Music, Venue Booking, Decor, Photography Services, Honeymoon, Service Staff, Invitations, Catering, PR And Media Coverage, Gifts, Celebrity Invites", "Planning Type": "Consultant, Coordination, Full Planning, Partial Planning", "Destination Wedding": "No", "Cities Worked": "Pune"}}, {"Planner Name": "UrbanCult Events", "Planner Location": "Hadapsar, Pune", "Price": "1,00,000", "Services": {"Starting Price": "₹1,00,000"}, "Offerings": ["Trousseau Preparations", "DJ/Music", "Venue Booking", "Decor", "Photography Services", "Honeymoon", "Service Staff", "Invitations", "Catering", "PR and Media Coverage", "Gifts", "Celebrity Invites"], "Policies": ["80% Payment On Booking", "Cancellation Policy - Depends On Situation", "20% Payment On Date"], "Other Information": {"In House Services": "Trousseau Preparations, DJ/Music, Venue Booking, Decor, Photography Services, Honeymoon, Service Staff, Invitations, Catering", "Planning Type": "Full Planning", "Cities Worked": "Pune"}}]