[{"Planner Name": "Fusion Wedding Planners", "Planner Location": "Ramanathapuram, Coimbatore", "Price": "4,99,999", "Services": {"Starting Price": "₹4,99,999"}, "Offerings": ["Trousseau Preparations", "DJ/Music", "Venue Booking", "Decor", "Photography Services", "Service Staff", "Invitations", "Catering"], "Policies": ["20% Payment On Booking", "80% Payment On Date", "Payment After Event - 0", "Cancellation Policy - Nego"], "Other Information": {"In House Services": "Trousseau Preparations, DJ/Music, Venue Booking, Decor, Photography Services, Service Staff, Invitations, Catering", "Planning Type": "Full Planning", "Cities Worked": "Chennai"}}]